scroll_term/__init__.py
scroll_term/cli.py
scroll_term-0.1.3.dist-info/entry_points.txt
scroll_term-0.1.3.dist-info/WHEEL
scroll_term-0.1.3.dist-info/METADATA
scroll_term-0.1.3.dist-info/RECORD
