Metadata-Version: 2.1
Name: scroll-term
Version: 0.1.3
Summary: scroll stdout!
Home-page: https://github.com/redraw/scroll
Author: redraw
Author-email: redraw@sdf.org
Requires-Python: >=3.6,<4.0
Classifier: Programming Language :: Python :: 3
Classifier: Programming Language :: Python :: 3.10
Classifier: Programming Language :: Python :: 3.6
Classifier: Programming Language :: Python :: 3.7
Classifier: Programming Language :: Python :: 3.8
Classifier: Programming Language :: Python :: 3.9
